[
 {
   "city": "Birmingham_AL",
   "latitude": 33.518589,
   "longitude": -86.810356
 },
 {
   "city": "Mobile_AL",
   "latitude": 30.695366,
   "longitude": -88.039894
 },
 {
   "city": "Phoenix_AZ",
   "latitude": 33.448376,
   "longitude": -112.074036
 },
 {
   "city": "LosAngeles_CA",
   "latitude": 34.052235,
   "longitude": -118.243683
 },
 {
   "city": "SanFrancisco_CA",
   "latitude": 37.7562,
   "longitude": -122.443
 },
 {
   "city": "SanDiego_CA",
   "latitude": 32.8312,
   "longitude": -117.1225
 },
 {
   "city": "Sacramento_CA",
   "latitude": 38.5667,
   "longitude": -121.4683
 },
 {
   "city": "Fresno_CA",
   "latitude": 36.7831,
   "longitude": -119.7941
 },
 {
   "city": "Denver_CO",
   "latitude": 38.8674,
   "longitude": -104.7606
 },
 {
   "city": "NewHaven_CT",
   "latitude": 41.3112,
   "longitude": -72.9246
 },
 {
   "city": "Miami_FL",
   "latitude": 25.8696,
   "longitude": -80.3046
 },
 {
   "city": "Jacksonville_FL",
   "latitude": 30.3322,
   "longitude": -81.6557
 },
 {
   "city": "Tampa_FL",
   "latitude": 27.9506,
   "longitude": -82.4572
 },
 {
   "city": "Orlando_FL",
   "latitude": 28.4772,
   "longitude": -81.3369
 },
 {
   "city": "Tallahassee_FL",
   "latitude": 30.4383,
   "longitude": -84.2807
 },
 {
   "city": "Atlanta_GA",
   "latitude": 33.749,
   "longitude": -84.388
 },
 {
   "city": "Boise_ID",
   "latitude": 43.615,
   "longitude": -116.2023
 },
 {
   "city": "Chicago_IL",
   "latitude": 41.8373,
   "longitude": -87.6862
 },
 {
   "city": "Indianapolis_IN",
   "latitude": 39.7771,
   "longitude": -86.1458
 },
 {
   "city": "DesMoines_IA",
   "latitude": 41.5868,
   "longitude": -93.625
 },
 {
   "city": "Wichita_KS",
   "latitude": 37.6872,
   "longitude": -97.3301
 },
 {
   "city": "Louisville_KY",
   "latitude": 38.2527,
   "longitude": -85.7585
 },
 {
   "city": "NewOrleans_LA",
   "latitude": 30.0687,
   "longitude": -89.9288
 },
 {
   "city": "Baltimore_MD",
   "latitude": 39.2904,
   "longitude": -76.6122
 },
 {
   "city": "Boston_MA",
   "latitude": 42.3601,
   "longitude": -71.0589
 },
 {
   "city": "Detroit_MI",
   "latitude": 42.3314,
   "longitude": -83.0458
 },
 {
   "city": "GrandRapids_MI",
   "latitude": 42.9634,
   "longitude": -85.6681
 },
 {
   "city": "Minneapolis_MN",
   "latitude": 44.9778,
   "longitude": -93.265
 },
 {
   "city": "Jackson_MS",
   "latitude": 32.2988,
   "longitude": -90.1848
 },
 {
   "city": "KansasCity_MO",
   "latitude": 39.0997,
   "longitude": -94.5786
 },
 {
   "city": "StLouis_MO",
   "latitude": 38.627,
   "longitude": -90.1994
 },
 {
   "city": "Springfield_MO",
   "latitude": 37.209,
   "longitude": -93.2923
 },
 {
   "city": "Billings_MT",
   "latitude": 45.7833,
   "longitude": -108.5007
 },
 {
   "city": "Omaha_NE",
   "latitude": 41.2565,
   "longitude": -95.9345
 },
 {
   "city": "LasVegas_NV",
   "latitude": 36.1699,
   "longitude": -115.1398
 },
 {
   "city": "Reno_NV",
   "latitude": 39.5296,
   "longitude": -119.8138
 },
 {
   "city": "Albuquerque_MN",
   "latitude": 35.0844,
   "longitude": -106.6504
 },
 {
   "city": "NewYorkCity_NY",
   "latitude": 40.7128,
   "longitude": -74.006
 },
 {
   "city": "Buffalo_NY",
   "latitude": 42.8864,
   "longitude": -78.8784
 },
 {
   "city": "Syracuse_NY",
   "latitude": 43.0481,
   "longitude": -76.1474
 },
 {
   "city": "Raleigh_NC",
   "latitude": 35.7796,
   "longitude": -78.6382
 },
 {
   "city": "Charlotte_NC",
   "latitude": 35.2271,
   "longitude": -80.8431
 },
 {
   "city": "Wilmington_NC",
   "latitude": 34.2104,
   "longitude": -77.8868
 },
 {
   "city": "Fargo_ND",
   "latitude": 46.8772,
   "longitude": -96.7898
 },
 {
   "city": "Columbus_OH",
   "latitude": 39.9612,
   "longitude": -82.9988
 },
 {
   "city": "Cleveland_OH",
   "latitude": 41.4993,
   "longitude": -81.6944
 },
 {
   "city": "Cincinnati_OH",
   "latitude": 39.1031,
   "longitude": -84.512
 },
 {
   "city": "OklahomaCity_OK",
   "latitude": 35.4676,
   "longitude": -97.5164
 },
 {
   "city": "Portland_OR",
   "latitude": 45.5051,
   "longitude": -122.675
 },
 {
   "city": "Philadelphia_PA",
   "latitude": 39.9526,
   "longitude": -75.1652
 },
 {
   "city": "Pittsburgh_PA",
   "latitude": 40.4406,
   "longitude": -79.9959
 },
 {
   "city": "Charleston_SC",
   "latitude": 32.7765,
   "longitude": -79.9311
 },
 {
   "city": "Columbia_SC",
   "latitude": 45.613,
   "longitude": -98.3126
 },
 {
   "city": "SiouxFalls_SD",
   "latitude": 43.546,
   "longitude": -96.7313
 },
 {
   "city": "Nashville_TN",
   "latitude": 36.1627,
   "longitude": -86.7816
 },
 {
   "city": "Memphis_TN",
   "latitude": 35.1495,
   "longitude": -90.049
 },
 {
   "city": "Knoxville_TN",
   "latitude": 35.9606,
   "longitude": -83.9207
 },
 {
   "city": "Dallas_TX",
   "latitude": 32.7767,
   "longitude": -96.797
 },
 {
   "city": "Houston_TX",
   "latitude": 29.7604,
   "longitude": -95.3698
 },
 {
   "city": "SanAntonio_TX",
   "latitude": 29.4241,
   "longitude": -98.4936
 },
 {
   "city": "Austin_TX",
   "latitude": 30.2672,
   "longitude": -97.7431
 },
 {
   "city": "Lubbock_TX",
   "latitude": 33.5779,
   "longitude": -101.8552
 },
 {
   "city": "El Paso_TX",
   "latitude": 31.7619,
   "longitude": -106.485
 },
 {
   "city": "SaltLakeCity_UT",
   "latitude": 40.7608,
   "longitude": -111.891
 },
 {
   "city": "VirginiaBeach_VA",
   "latitude": 36.8529,
   "longitude": -75.978
 },
 {
   "city": "Richmond_VA",
   "latitude": 37.5407,
   "longitude": -77.436
 },
 {
   "city": "Seattle_WA",
   "latitude": 47.6062,
   "longitude": -122.3321
 },
 {
   "city": "Spokane_WA",
   "latitude": 47.6588,
   "longitude": -117.426
 },
 {
   "city": "Milwaukee_WI",
   "latitude": 43.0389,
   "longitude": -87.9065
 },
 {
   "city": "Madison_WI",
   "latitude": 43.0731,
   "longitude": -89.4012
 },
 {
   "city": "Green Bay_WI",
   "latitude": 44.5133,
   "longitude": -88.0133
 }
]